starrydata/__init__.py
starrydata/dataset.py
starrydata/test_dataset.py
starrydata-1.4.0.dist-info/LICENSE
starrydata-1.4.0.dist-info/METADATA
starrydata-1.4.0.dist-info/WHEEL
starrydata-1.4.0.dist-info/top_level.txt
starrydata-1.4.0.dist-info/RECORD
