Metadata-Version: 2.1
Name: starrydata
Version: 1.4.0
Summary: Starrydata Python useful tools 
Author-email: MATO Tomoya <tomoya.matou@gmail.com>
Project-URL: Homepage, https://github.com/starrydata/starrydata-python-library
Project-URL: Issues, https://github.com/starrydata/starrydata-python-library/issues
Classifier: Programming Language :: Python :: 3
Classifier: License :: OSI Approved :: MIT License
Classifier: Operating System :: OS Independent
Requires-Python: >=3.8
License-File: LICENSE
Requires-Dist: requests
Requires-Dist: tqdm >=4.0.0
